README.rst
setup.py
hisser/__init__.py
hisser/agg.py
hisser/blocks.py
hisser/buffer.py
hisser/cli.py
hisser/config.py
hisser/db.py
hisser/defaults.py
hisser/graphite.py
hisser/metrics.py
hisser/server.py
hisser/utils.py
hisser.egg-info/PKG-INFO
hisser.egg-info/SOURCES.txt
hisser.egg-info/dependency_links.txt
hisser.egg-info/entry_points.txt
hisser.egg-info/requires.txt
hisser.egg-info/top_level.txt