Metadata-Version: 1.1
Name: hisser
Version: 0.9
Summary: Fast TSDB backend for graphite
Home-page: https://github.com/baverman/hisser
Author: Anton Bobrov
Author-email: baverman@gmail.com
License: MIT
Platform: UNKNOWN
Classifier: Intended Audience :: Developers
Classifier: Natural Language :: English
Classifier: License :: OSI Approved :: MIT License
Classifier: Programming Language :: Python
Classifier: Programming Language :: Python :: 3
Classifier: Programming Language :: Python :: 3.5
Classifier: Programming Language :: Python :: 3.6
